{
  "name": "Environment, Conservation and Parks",
  "slug": "environment-conservation-and-parks",
  "totalSpending": 0.492531089,
  "totalSpendingFormatted": "$0.5B",
  "percentage": 0.24548633415921503,
  "percentageFormatted": "0.2%",
  "categories": [
    {
      "name": "Operations",
      "amount": 0.187051081
    },
    {
      "name": "Operations",
      "amount": 0.06398518599999999
    },
    {
      "name": "Operations",
      "amount": 0.06050630799999999
    },
    {
      "name": "Operations",
      "amount": 0.045549055
    },
    {
      "name": "Operations",
      "amount": 0.035508636
    },
    {
      "name": "Operations",
      "amount": 0.014806664
    },
    {
      "name": "Operations",
      "amount": 0.012667458000000001
    },
    {
      "name": "Conservation Partnership – Capital",
      "amount": 0.012655
    },
    {
      "name": "Wastewater Surveillance Initiative",
      "amount": 0.011763356
    },
    {
      "name": "Species at Risk Stewardship Program",
      "amount": 0.008382677
    },
    {
      "name": "Great Lakes - General",
      "amount": 0.007039722
    },
    {
      "name": "Wetland Conservation Partner Program",
      "amount": 0.006671544
    },
    {
      "name": "Conservation Partnership",
      "amount": 0.006345
    },
    {
      "name": "Drinking Water Source Protection",
      "amount": 0.005938207
    },
    {
      "name": "Walkerton Clean Water Centre",
      "amount": 0.0056
    },
    {
      "name": "Environmental Remediation – Capital",
      "amount": 0.0035
    },
    {
      "name": "Environmental Planning and Action",
      "amount": 0.002
    },
    {
      "name": "Lake Simcoe - General",
      "amount": 0.0012377
    },
    {
      "name": "Other",
      "amount": 0.000959495
    },
    {
      "name": "Other",
      "amount": 0.000124
    },
    {
      "name": "Other",
      "amount": 0.000123
    },
    {
      "name": "Other",
      "amount": 0.000087
    },
    {
      "name": "Other",
      "amount": 0.00003
    }
  ],
  "spending_data": {
    "name": "Environment, Conservation and Parks",
    "children": [
      {
        "name": "Operations",
        "amount": 0.187051081
      },
      {
        "name": "Operations",
        "amount": 0.06398518599999999
      },
      {
        "name": "Operations",
        "amount": 0.06050630799999999
      },
      {
        "name": "Operations",
        "amount": 0.045549055
      },
      {
        "name": "Operations",
        "amount": 0.035508636
      },
      {
        "name": "Operations",
        "amount": 0.014806664
      },
      {
        "name": "Operations",
        "amount": 0.012667458000000001
      },
      {
        "name": "Conservation Partnership – Capital",
        "amount": 0.012655
      },
      {
        "name": "Wastewater Surveillance Initiative",
        "amount": 0.011763356
      },
      {
        "name": "Species at Risk Stewardship Program",
        "amount": 0.008382677
      },
      {
        "name": "Great Lakes - General",
        "amount": 0.007039722
      },
      {
        "name": "Wetland Conservation Partner Program",
        "amount": 0.006671544
      },
      {
        "name": "Conservation Partnership",
        "amount": 0.006345
      },
      {
        "name": "Drinking Water Source Protection",
        "amount": 0.005938207
      },
      {
        "name": "Walkerton Clean Water Centre",
        "amount": 0.0056
      },
      {
        "name": "Environmental Remediation – Capital",
        "amount": 0.0035
      },
      {
        "name": "Environmental Planning and Action",
        "amount": 0.002
      },
      {
        "name": "Lake Simcoe - General",
        "amount": 0.0012377
      },
      {
        "name": "Other",
        "amount": 0.000959495
      },
      {
        "name": "Other",
        "amount": 0.000124
      },
      {
        "name": "Other",
        "amount": 0.000123
      },
      {
        "name": "Other",
        "amount": 0.000087
      },
      {
        "name": "Other",
        "amount": 0.00003
      }
    ]
  }
}