{
  "name": "Transportation",
  "slug": "transportation",
  "totalSpending": 12.073573912999997,
  "totalSpendingFormatted": "$12.1B",
  "percentage": 6.017685921350437,
  "percentageFormatted": "6.0%",
  "categories": [
    {
      "name": "Metrolinx",
      "amount": 6.580035232
    },
    {
      "name": "Operations",
      "amount": 1.290519797
    },
    {
      "name": "Metrolinx Operating Subsidies",
      "amount": 1.221041938
    },
    {
      "name": "Operations",
      "amount": 0.717104283
    },
    {
      "name": "Municipal Transit",
      "amount": 0.598928827
    },
    {
      "name": "Municipal Public Transportation Funding",
      "amount": 0.379402392
    },
    {
      "name": "Municipal Public Transportation Funding, the Dedicated Funding for Public Transportation Act",
      "amount": 0.374432931
    },
    {
      "name": "Municipal Transit",
      "amount": 0.3
    },
    {
      "name": "Highways and Land Transfers",
      "amount": 0.1975
    },
    {
      "name": "Operations",
      "amount": 0.17497806400000002
    },
    {
      "name": "Operations",
      "amount": 0.149904395
    },
    {
      "name": "Ontario Northland Transportation Commission",
      "amount": 0.102675795
    },
    {
      "name": "Operations",
      "amount": 0.069078694
    },
    {
      "name": "Operations",
      "amount": 0.061872892000000006
    },
    {
      "name": "Ontario Northland Transportation Commission",
      "amount": 0.059582375
    },
    {
      "name": "Operations",
      "amount": 0.02702053
    },
    {
      "name": "Connecting Links",
      "amount": 0.026752308
    },
    {
      "name": "Payments in lieu of Municipal Taxation",
      "amount": 0.012267598
    },
    {
      "name": "Owen Sound Transportation Company",
      "amount": 0.011505195
    },
    {
      "name": "Transition Fund",
      "amount": 0.01
    },
    {
      "name": "Third Party Operating Highway Works",
      "amount": 0.0069
    },
    {
      "name": "Municipal Ferries",
      "amount": 0.006517099
    },
    {
      "name": "Owen Sound Transportation Company",
      "amount": 0.005907097
    },
    {
      "name": "First Nations",
      "amount": 0.005704395
    },
    {
      "name": "Community Transportation Grant Program",
      "amount": 0.004807227
    },
    {
      "name": "Ontario Seniors Public Transit Tax Credit",
      "amount": 0.0045843
    },
    {
      "name": "Other",
      "amount": 0.000770331
    },
    {
      "name": "Other",
      "amount": 0.000506626
    },
    {
      "name": "Other",
      "amount": 0.00038573000000000004
    },
    {
      "name": "Operations",
      "amount": -0.327112138
    }
  ],
  "spending_data": {
    "name": "Transportation",
    "children": [
      {
        "name": "Metrolinx",
        "amount": 6.580035232
      },
      {
        "name": "Operations",
        "amount": 1.290519797
      },
      {
        "name": "Metrolinx Operating Subsidies",
        "amount": 1.221041938
      },
      {
        "name": "Operations",
        "amount": 0.717104283
      },
      {
        "name": "Municipal Transit",
        "amount": 0.598928827
      },
      {
        "name": "Municipal Public Transportation Funding",
        "amount": 0.379402392
      },
      {
        "name": "Municipal Public Transportation Funding, the Dedicated Funding for Public Transportation Act",
        "amount": 0.374432931
      },
      {
        "name": "Municipal Transit",
        "amount": 0.3
      },
      {
        "name": "Highways and Land Transfers",
        "amount": 0.1975
      },
      {
        "name": "Operations",
        "amount": 0.17497806400000002
      },
      {
        "name": "Operations",
        "amount": 0.149904395
      },
      {
        "name": "Ontario Northland Transportation Commission",
        "amount": 0.102675795
      },
      {
        "name": "Operations",
        "amount": 0.069078694
      },
      {
        "name": "Operations",
        "amount": 0.061872892000000006
      },
      {
        "name": "Ontario Northland Transportation Commission",
        "amount": 0.059582375
      },
      {
        "name": "Operations",
        "amount": 0.02702053
      },
      {
        "name": "Connecting Links",
        "amount": 0.026752308
      },
      {
        "name": "Payments in lieu of Municipal Taxation",
        "amount": 0.012267598
      },
      {
        "name": "Owen Sound Transportation Company",
        "amount": 0.011505195
      },
      {
        "name": "Transition Fund",
        "amount": 0.01
      },
      {
        "name": "Third Party Operating Highway Works",
        "amount": 0.0069
      },
      {
        "name": "Municipal Ferries",
        "amount": 0.006517099
      },
      {
        "name": "Owen Sound Transportation Company",
        "amount": 0.005907097
      },
      {
        "name": "First Nations",
        "amount": 0.005704395
      },
      {
        "name": "Community Transportation Grant Program",
        "amount": 0.004807227
      },
      {
        "name": "Ontario Seniors Public Transit Tax Credit",
        "amount": 0.0045843
      },
      {
        "name": "Other",
        "amount": 0.000770331
      },
      {
        "name": "Other",
        "amount": 0.000506626
      },
      {
        "name": "Other",
        "amount": 0.00038573000000000004
      },
      {
        "name": "Operations",
        "amount": -0.327112138
      }
    ]
  }
}